eldarutils/__init__.py
eldarutils/listutils.py
eldarutils/stringutils.py
eldarutils-0.1.0.dist-info/METADATA
eldarutils-0.1.0.dist-info/WHEEL
eldarutils-0.1.0.dist-info/top_level.txt
eldarutils-0.1.0.dist-info/RECORD
